OmerBlack/Apihelpers.py
OmerBlack/BinanceTrRequests.py
OmerBlack/BinanceTrService.py
OmerBlack/TimeModel.py
OmerBlack/UserModel.py
OmerBlack/__init__.py
OmerBlack/config.py
OmerBlack/constants.json
OmerBlack-2.0.dist-info/LICENSE
OmerBlack-2.0.dist-info/METADATA
OmerBlack-2.0.dist-info/WHEEL
OmerBlack-2.0.dist-info/top_level.txt
OmerBlack-2.0.dist-info/RECORD
